context_logger/__init__.py
context_logger/context_logger.py
context_logger/context_threading.py
context_logger/decorators.py
py_context_logger-2.0.0.dist-info/LICENSE
py_context_logger-2.0.0.dist-info/METADATA
py_context_logger-2.0.0.dist-info/WHEEL
py_context_logger-2.0.0.dist-info/top_level.txt
py_context_logger-2.0.0.dist-info/RECORD
