Metadata-Version: 2.1
Name: py-context-logger
Version: 2.0.0
Summary: A python context logger with thread-local storage and context propagation for Python applications.
Home-page: https://github.com/RajeshKumar1490/py-context-logger
Author: Rajesh Ganjikunta
Author-email: rajeshkumarganjikunta90@gmail.com
License: MIT
Classifier: Development Status :: 3 - Alpha
Classifier: Intended Audience :: Developers
Classifier: License :: OSI Approved :: MIT License
Classifier: Programming Language :: Python :: 3
Classifier: Programming Language :: Python :: 3.7
Classifier: Programming Language :: Python :: 3.8
Classifier: Programming Language :: Python :: 3.9
Classifier: Programming Language :: Python :: 3.10
Classifier: Programming Language :: Python :: 3.11
License-File: LICENSE
